[
  {
    "????": "2025?5?",
    "????": "66150",
    "???": "5?2?",
    "??": "",
    "??": "??",
    "BK": "???",
    "???????": "?????????????"
  },
  {
    "????": "2025?5?",
    "????": "66217",
    "???": "5?3?",
    "??": "??",
    "??": "??",
    "BK": "????",
    "???????": "???"
  },
  {
    "????": "2025?5?",
    "????": "66223",
    "???": "5?3?",
    "??": "??",
    "??": "",
    "BK": "???",
    "???????": "?????????????"
  },
  {
    "????": "2025?5?",
    "????": "66225",
    "???": "5?3?",
    "??": "??",
    "??": "??",
    "BK": "????",
    "???????": "???"
  },
  {
    "????": "2025?5?",
    "????": "66243",
    "???": "5?4?",
    "??": "??",
    "??": "??",
    "BK": "????",
    "???????": "???"
  },
  {
    "????": "2025?5?",
    "????": "66254_55",
    "???": "5?4?",
    "??": "??",
    "??": "??",
    "BK": "???",
    "???????": "?????????????"
  },
  {
    "????": "2025?5?",
    "????": "66263",
    "???": "5?4?",
    "??": "??",
    "??": "??",
    "BK": "????",
    "???????": "???"
  },
  {
    "????": "2025?5?",
    "????": "66267",
    "???": "5?4?",
    "??": "??",
    "??": "??",
    "BK": "???",
    "???????": "?????????????"
  },
  {
    "????": "2025?5?",
    "????": "66313_14",
    "???": "5?5?",
    "??": "??",
    "??": "??",
    "BK": "???",
    "???????": "?????????????"
  },
  {
    "????": "2025?5?",
    "????": "66358",
    "???": "5?5?",
    "??": "??",
    "??": "??",
    "BK": "???",
    "???????": "?????????????"
  },
  {
    "????": "2025?5?",
    "????": "66377",
    "???": "5?5?",
    "??": "??",
    "??": "??",
    "BK": "????",
    "???????": "???"
  },
  {
    "????": "2025?5?",
    "????": "66436",
    "???": "5?6?",
    "??": "??",
    "??": "??",
    "BK": "????",
    "???????": "???"
  },
  {
    "????": "2025?5?",
    "????": "66503",
    "???": "5?10?",
    "??": "??",
    "??": "??",
    "BK": "????",
    "???????": "???"
  },
  {
    "????": "2025?5?",
    "????": "66527",
    "???": "5?11?",
    "??": "??",
    "??": "??",
    "BK": "???",
    "???????": "?????????????"
  },
  {
    "????": "2025?5?",
    "????": "66535",
    "???": "5?11?",
    "??": "??",
    "??": "??",
    "BK": "????",
    "???????": "???"
  },
  {
    "????": "2025?5?",
    "????": "66608",
    "???": "5?10?",
    "??": "?",
    "??": "??",
    "BK": "???",
    "???????": "?????????????"
  },
  {
    "????": "2025?5?",
    "????": "66627",
    "???": "5?11?",
    "??": "??",
    "??": "??",
    "BK": "????",
    "???????": "?????????????"
  },
  {
    "????": "2025?5?",
    "????": "66636",
    "???": "5?11?",
    "??": "???",
    "??": "???",
    "BK": "????",
    "???????": "?????????????"
  },
  {
    "????": "2025?5?",
    "????": "66690",
    "???": "5?17?",
    "??": "??",
    "??": "??",
    "BK": "???",
    "???????": "?????????????"
  },
  {
    "????": "2025?5?",
    "????": "66715",
    "???": "5?17?",
    "??": "??",
    "??": "??",
    "BK": "???",
    "???????": "?????????????"
  },
  {
    "????": "2025?5?",
    "????": "66758",
    "???": "5?18?",
    "??": "??",
    "??": "??",
    "BK": "???",
    "???????": "?????????????"
  },
  {
    "????": "2025?5?",
    "????": "66762",
    "???": "5?18?",
    "??": "??",
    "??": "??",
    "BK": "????",
    "???????": "???"
  },
  {
    "????": "2025?5?",
    "????": "66776",
    "???": "5?18?",
    "??": "??",
    "??": "??",
    "BK": "???",
    "???????": "?????????????"
  },
  {
    "????": "2025?5?",
    "????": "66798",
    "???": "5?18?",
    "??": "??",
    "??": "??",
    "BK": "????",
    "???????": "???"
  },
  {
    "????": "2025?5?",
    "????": "66802",
    "???": "5?18?",
    "??": "??",
    "??": "??",
    "BK": "???",
    "???????": "?????????????"
  },
  {
    "????": "2025?5?",
    "????": "66816",
    "???": "5?17?",
    "??": "??",
    "??": "??",
    "BK": "????",
    "???????": "???"
  },
  {
    "????": "2025?5?",
    "????": "66822",
    "???": "5?18?",
    "??": "??",
    "??": "??",
    "BK": "???",
    "???????": "?????????????"
  },
  {
    "????": "2025?5?",
    "????": "66823",
    "???": "5?18?",
    "??": "??",
    "??": "?",
    "BK": "???",
    "???????": "?????????????"
  },
  {
    "????": "2025?5?",
    "????": "66870",
    "???": "5?18?",
    "??": "??",
    "??": "??",
    "BK": "????",
    "???????": "???"
  },
  {
    "????": "2025?5?",
    "????": "66877",
    "???": "5?23?",
    "??": "??",
    "??": "??",
    "BK": "???",
    "???????": "?????????????"
  },
  {
    "????": "2025?5?",
    "????": "66879",
    "???": "5?23?",
    "??": "??",
    "??": "??",
    "BK": "???",
    "???????": "?????????????"
  },
  {
    "????": "2025?5?",
    "????": "66881",
    "???": "5?24?",
    "??": "??",
    "??": "",
    "BK": "???",
    "???????": "?????????????"
  },
  {
    "????": "2025?5?",
    "????": "66882",
    "???": "5?24?",
    "??": "??",
    "??": "??",
    "BK": "????",
    "???????": "?????????"
  },
  {
    "????": "2025?5?",
    "????": "66885",
    "???": "5?24?",
    "??": "??",
    "??": "??",
    "BK": "????",
    "???????": "???"
  },
  {
    "????": "2025?5?",
    "????": "66909",
    "???": "5?24?",
    "??": "??",
    "??": "??",
    "BK": "???",
    "???????": "?????????????"
  },
  {
    "????": "2025?5?",
    "????": "66945",
    "???": "5?22?",
    "??": "??",
    "??": "??",
    "BK": "???",
    "???????": "?????????????"
  },
  {
    "????": "2025?5?",
    "????": "66958",
    "???": "5?25?",
    "??": "??",
    "??": "??",
    "BK": "????",
    "???????": "???"
  },
  {
    "????": "2025?5?",
    "????": "66996",
    "???": "5?25?",
    "??": "??",
    "??": "??",
    "BK": "????",
    "???????": "???"
  },
  {
    "????": "2025?5?",
    "????": "67008",
    "???": "5?25?",
    "??": "???",
    "??": "??",
    "BK": "???",
    "???????": "?????????????"
  },
  {
    "????": "2025?5?",
    "????": "67011",
    "???": "5?25?",
    "??": "??",
    "??": "??",
    "BK": "????",
    "???????": "???"
  },
  {
    "????": "2025?5?",
    "????": "67012",
    "???": "5?25?",
    "??": "??",
    "??": "??",
    "BK": "????",
    "???????": "???"
  },
  {
    "????": "2025?5?",
    "????": "67037",
    "???": "5?25?",
    "??": "??",
    "??": "??",
    "BK": "????",
    "???????": "???"
  },
  {
    "????": "2025?5?",
    "????": "67041",
    "???": "5?24?",
    "??": "??",
    "??": "???",
    "BK": "???",
    "???????": "?????????????"
  },
  {
    "????": "2025?5?",
    "????": "67049",
    "???": "5?26?",
    "??": "??",
    "??": "??",
    "BK": "???",
    "???????": "?????????????"
  },
  {
    "????": "2025?5?",
    "????": "67053",
    "???": "5?24?",
    "??": "??",
    "??": "??",
    "BK": "???",
    "???????": "???"
  },
  {
    "????": "2025?5?",
    "????": "67060",
    "???": "5?24?",
    "??": "??",
    "??": "??",
    "BK": "????",
    "???????": "?????????????"
  },
  {
    "????": "2025?5?",
    "????": "67074",
    "???": "5?28?",
    "??": "??",
    "??": "??",
    "BK": "???",
    "???????": "?????????????"
  },
  {
    "????": "2025?5?",
    "????": "67079",
    "???": "5?25?",
    "??": "??",
    "??": "??",
    "BK": "???",
    "???????": "?????????????"
  },
  {
    "????": "2025?5?",
    "????": "67155",
    "???": "5?31?",
    "??": "??",
    "??": "??",
    "BK": "???",
    "???????": "?????????????"
  },
  {
    "????": "2025?5?",
    "????": "67184",
    "???": "5?31?",
    "??": "??",
    "??": "??",
    "BK": "????",
    "???????": "???"
  },
  {
    "????": "2025?5?",
    "????": "67018",
    "???": "5?24?",
    "??": "??",
    "??": "??",
    "BK": "????",
    "???????": "???"
  },
  {
    "????": "2025?5?",
    "????": "67443",
    "???": "5?18?",
    "??": "??",
    "??": "??",
    "BK": "???",
    "???????": "?????????"
  }
]